wmsdump/__init__.py
wmsdump/_version.py
wmsdump/capabilities.py
wmsdump/cli.py
wmsdump/deduplicate.py
wmsdump/dumper.py
wmsdump/errors.py
wmsdump/georss_helper.py
wmsdump/geoserver.py
wmsdump/hole_puncher.py
wmsdump/kml_helper.py
wmsdump/logging.py
wmsdump/props_helper.py
wmsdump/state.py
wmsdump-0.1.4.dist-info/METADATA
wmsdump-0.1.4.dist-info/WHEEL
wmsdump-0.1.4.dist-info/entry_points.txt
wmsdump-0.1.4.dist-info/licenses/LICENSE
wmsdump-0.1.4.dist-info/RECORD
