Metadata-Version: 2.4
Name: wmsdump
Version: 0.1.4
Summary: Library for extraction of data from WMS/WFS endpoints
Project-URL: homepage, https://github.com/ramSeraph/pywmsdump
Project-URL: repository, https://github.com/ramSeraph/pywmsdump.git
Author-email: Sreeram Kandimalla <kandimalla.sreeram@gmail.com>
License: This is free and unencumbered software released into the public domain.
License-File: LICENSE
Requires-Python: >=3.12
Requires-Dist: bs4>=0.0.2
Requires-Dist: click>=8.1.7
Requires-Dist: colorlog>=6.9.0
Requires-Dist: jsonschema>=4.23.0
Requires-Dist: kml2geojson>=5.1.0
Requires-Dist: requests>=2.32.3
Requires-Dist: xmltodict>=0.14.2
Provides-Extra: proj
Requires-Dist: pyproj>=3.7.0; extra == 'proj'
Provides-Extra: punch-holes
Requires-Dist: geoindex-rs>=0.2.0; extra == 'punch-holes'
Requires-Dist: numpy>=2.2.1; extra == 'punch-holes'
Requires-Dist: shapely>=2.0.6; extra == 'punch-holes'
